build/lib/build/lib/build/lib/build/lib/build/lib/build/lib/build/lib/build/lib/build/lib/jandd/sphinxext/ip/__init__.py
build/lib/build/lib/build/lib/build/lib/build/lib/build/lib/build/lib/build/lib/build/lib/tests/__init__.py
build/lib/build/lib/build/lib/build/lib/build/lib/build/lib/build/lib/build/lib/build/lib/tests/run.py
build/lib/build/lib/build/lib/build/lib/build/lib/build/lib/build/lib/build/lib/build/lib/tests/test_ip.py
build/lib/build/lib/build/lib/build/lib/build/lib/build/lib/build/lib/build/lib/build/lib/tests/util.py
build/lib/build/lib/build/lib/build/lib/build/lib/build/lib/build/lib/build/lib/build/lib/tests/root/conf.py
build/lib/build/lib/build/lib/build/lib/build/lib/build/lib/build/lib/build/lib/jandd/sphinxext/ip/__init__.py
build/lib/build/lib/build/lib/build/lib/build/lib/build/lib/build/lib/build/lib/tests/__init__.py
build/lib/build/lib/build/lib/build/lib/build/lib/build/lib/build/lib/build/lib/tests/run.py
build/lib/build/lib/build/lib/build/lib/build/lib/build/lib/build/lib/build/lib/tests/test_ip.py
build/lib/build/lib/build/lib/build/lib/build/lib/build/lib/build/lib/build/lib/tests/util.py
build/lib/build/lib/build/lib/build/lib/build/lib/build/lib/build/lib/build/lib/tests/root/conf.py
build/lib/build/lib/build/lib/build/lib/build/lib/build/lib/build/lib/jandd/sphinxext/ip/__init__.py
build/lib/build/lib/build/lib/build/lib/build/lib/build/lib/build/lib/tests/__init__.py
build/lib/build/lib/build/lib/build/lib/build/lib/build/lib/build/lib/tests/run.py
build/lib/build/lib/build/lib/build/lib/build/lib/build/lib/build/lib/tests/test_ip.py
build/lib/build/lib/build/lib/build/lib/build/lib/build/lib/build/lib/tests/util.py
build/lib/build/lib/build/lib/build/lib/build/lib/build/lib/build/lib/tests/root/conf.py
build/lib/build/lib/build/lib/build/lib/build/lib/build/lib/jandd/sphinxext/ip/__init__.py
build/lib/build/lib/build/lib/build/lib/build/lib/build/lib/tests/__init__.py
jandd.sphinxext.ip-0.6.3.dist-info/COPYING
jandd.sphinxext.ip-0.6.3.dist-info/METADATA
jandd.sphinxext.ip-0.6.3.dist-info/WHEEL
jandd.sphinxext.ip-0.6.3.dist-info/top_level.txt
jandd.sphinxext.ip-0.6.3.dist-info/RECORD
