Metadata-Version: 2.1
Name: jandd.sphinxext.ip
Version: 0.6.3
Summary: IP address extension for Sphinx
Home-page: https://pypi.org/project/jandd.sphinxext.ip/
Author: Jan Dittberner
Author-email: jan@dittberner.info
License: GPLv3+
Keywords: sphinx,extension,IP
Platform: any
Classifier: Development Status :: 5 - Production/Stable
Classifier: Framework :: Sphinx :: Extension
Classifier: License :: OSI Approved :: GNU General Public License v3 or later (GPLv3+)
Classifier: Programming Language :: Python :: 3
Classifier: Topic :: Documentation
Classifier: Topic :: Internet
License-File: COPYING
Requires-Dist: Sphinx >=5
